LICENSE
MANIFEST.in
README.rst
requirements.txt
setup.py
temporary_email.egg-info/PKG-INFO
temporary_email.egg-info/SOURCES.txt
temporary_email.egg-info/dependency_links.txt
temporary_email.egg-info/requires.txt
temporary_email.egg-info/top_level.txt
temporaty_email/__init__.py
temporaty_email/temporary_email.py