Metadata-Version: 1.1
Name: temporary-email
Version: 0.5
Summary: A simple way to use temporary email.
Home-page: https://github.com/tongyongquan/temporary_email
Author: TongYongQuan
Author-email: 1070969926@qq.com
License: MIT License
Platform: UNKNOWN
Classifier: Intended Audience :: Developers
Classifier: License :: OSI Approved :: BSD License
Classifier: Operating System :: OS Independent
Classifier: Programming Language :: Python :: 3.5
Classifier: Topic :: Internet :: WWW/HTTP
Classifier: Topic :: Internet :: WWW/HTTP :: Dynamic Content
